pippa_api/__init__.py
pippa_api/client.py
pippa_api-0.1.0.dist-info/licenses/LICENSE
pippa_api-0.1.0.dist-info/METADATA
pippa_api-0.1.0.dist-info/WHEEL
pippa_api-0.1.0.dist-info/top_level.txt
pippa_api-0.1.0.dist-info/RECORD
