Metadata-Version: 2.4
Name: pippa-api
Version: 0.1.0
Summary: A simple wrapper library for the Pippa API.
Author-email: Dr Graeme Benstead-Hume <ghume@icr.ac.uk>
Project-URL: Homepage, https://github.com/mrgraeme/pippa_api
Project-URL: Issues, https://github.com/mrgraeme/pippa_api/issues
Classifier: Programming Language :: Python :: 3
Classifier: License :: OSI Approved :: MIT License
Classifier: Operating System :: OS Independent
Requires-Python: >=3.8
License-File: LICENSE
Requires-Dist: requests
Dynamic: license-file
